{
  "_class": "symbolInstance",
  "booleanOperation": -1,
  "do_objectID": "5287E6A7-6EA1-4554-95F9-23F427D4C889",
  "exportOptions": {
    "_class": "exportOptions",
    "exportFormats": [
    ],
    "includedLayerIds": [
    ],
    "layerOptions": 0,
    "shouldTrim": false
  },
  "frame": {
    "_class": "rect",
    "constrainProportions": false,
    "height": 14,
    "width": 224,
    "x": 14,
    "y": 368
  },
  "horizontalSpacing": 0,
  "isFixedToViewport": false,
  "isFlippedHorizontal": false,
  "isFlippedVertical": false,
  "isLocked": false,
  "isVisible": true,
  "layerListExpandedType": 0,
  "name": "Atom/error,message",
  "nameIsFixed": false,
  "overrideValues": [
    {
      "_class": "overrideValue",
      "do_objectID": "FB33B415-FB22-4549-936F-F495B7FD7D63",
      "overrideName": "7D83E076-A476-42BF-A40B-D62C60E08DB9_stringValue",
      "value": "Invalid Password Entry"
    }
  ],
  "resizingConstraint": 63,
  "resizingType": 0,
  "rotation": 0,
  "scale": 1,
  "shouldBreakMaskChain": false,
  "style": {
    "_class": "style",
    "endMarkerType": 0,
    "miterLimit": 10,
    "startMarkerType": 0,
    "windingRule": 1
  },
  "symbolID": "3581BE6C-32C8-4297-84CA-8ADD85BEFAFD",
  "verticalSpacing": 0
}